[
    {
        "name": "(TR-R) RADYO YUKSEL",
        "id": "trrradyoyuksel",
        "logo": "",
        "url": "http://ip.sltv.nl:8080/Momokuyen67/KisT5PeotB/166854",
        "categories": [
            "all radio"
        ],
        "country": ""
    },
    {
        "name": "(TR-R) SLOW KARADENIZ FM",
        "id": "trrslowkaradenizfm",
        "logo": "",
        "url": "http://ip.sltv.nl:8080/Momokuyen67/KisT5PeotB/166827",
        "categories": [
            "all radio"
        ],
        "country": ""
    },
    {
        "name": "(TR-R) TEKIRDAG RADYO CAN",
        "id": "trrtekirdagradyocan",
        "logo": "",
        "url": "http://ip.sltv.nl:8080/Momokuyen67/KisT5PeotB/166797",
        "categories": [
            "all radio"
        ],
        "country": ""
    },
    {
        "name": "(GR-Radio) KOSMORADIO 95.1",
        "id": "grradiokosmoradio951",
        "logo": "",
        "url": "http://ip.sltv.nl:8080/Momokuyen67/KisT5PeotB/161676",
        "categories": [
            "all radio"
        ],
        "country": ""
    },
    {
        "name": "(GR-Radio) STYL FM ATHENS 104.8",
        "id": "grradiostylfmathens1048",
        "logo": "",
        "url": "http://ip.sltv.nl:8080/Momokuyen67/KisT5PeotB/161677",
        "categories": [
            "all radio"
        ],
        "country": ""
    },
    {
        "name": "(TR-R) ERZINCAN INCITEK FM",
        "id": "trrerzincanincitekfm",
        "logo": "",
        "url": "http://ip.sltv.nl:8080/Momokuyen67/KisT5PeotB/167298",
        "categories": [
            "all radio"
        ],
        "country": ""
    },
    {
        "name": "(TR-R) GUL RADYO",
        "id": "trrgulradyo",
        "logo": "",
        "url": "http://ip.sltv.nl:8080/Momokuyen67/KisT5PeotB/167261",
        "categories": [
            "all radio"
        ],
        "country": ""
    },
    {
        "name": "(TR-R) HAMSFMI",
        "id": "trrhamsfmi",
        "logo": "",
        "url": "http://ip.sltv.nl:8080/Momokuyen67/KisT5PeotB/167259",
        "categories": [
            "all radio"
        ],
        "country": ""
    },
    {
        "name": "(TR-R) KLASIK HOME",
        "id": "trrklasikhome",
        "logo": "",
        "url": "http://ip.sltv.nl:8080/Momokuyen67/KisT5PeotB/134062",
        "categories": [
            "all radio"
        ],
        "country": ""
    },
    {
        "name": "(TR-R) RADYO IZMIR FM",
        "id": "trrradyoizmirfm",
        "logo": "",
        "url": "http://ip.sltv.nl:8080/Momokuyen67/KisT5PeotB/166941",
        "categories": [
            "all radio"
        ],
        "country": ""
    },
    {
        "name": "(TR-R) ULKU FM",
        "id": "trrulkufm",
        "logo": "",
        "url": "http://ip.sltv.nl:8080/Momokuyen67/KisT5PeotB/166741",
        "categories": [
            "all radio"
        ],
        "country": ""
    },
    {
        "name": "(GR-Radio) ANGEL 102.8 KARDITSA",
        "id": "grradioangel1028karditsa",
        "logo": "",
        "url": "http://ip.sltv.nl:8080/Momokuyen67/KisT5PeotB/161632",
        "categories": [
            "all radio"
        ],
        "country": ""
    },
    {
        "name": "(GR-Radio) RADIO ENERGEIA 106.4 KORINTHOS",
        "id": "grradioradioenergeia1064korinthos",
        "logo": "",
        "url": "http://ip.sltv.nl:8080/Momokuyen67/KisT5PeotB/161643",
        "categories": [
            "all radio"
        ],
        "country": ""
    },
    {
        "name": "(DK-Radio)  DR P2 Klassisk",
        "id": "dkradiodrp2klassisk",
        "logo": "https://via.ritzau.dk/data/images/00044/a0a230ae-4610-4fd3-ba97-a627d4771366-w_720.png",
        "url": "http://ip.sltv.nl:8080/Momokuyen67/KisT5PeotB/34757",
        "categories": [
            "all radio"
        ],
        "country": ""
    },
    {
        "name": "NL: NPO3 RADIO",
        "id": "nlnpo3radio",
        "logo": "",
        "url": "http://ip.sltv.nl:8080/Momokuyen67/KisT5PeotB/225109",
        "categories": [
            "all radio"
        ],
        "country": ""
    }
]