[
    {
        "name": "AR| سلمى (2025) S01 E30",
        "id": "ar2025s01e30",
        "logo": "https://image.tmdb.org/t/p/w185/ikLPBoxIzUL8OhIm21kV1V4TcIh.jpg",
        "url": "http://drz.flixip.icu:80/series/2h08bd3p9k/gxhviruvbg/1900947.ts",
        "categories": [
            "ar| سلمى (2025)"
        ],
        "country": ""
    },
    {
        "name": "AR| سلمى (2025) S01 E37",
        "id": "ar2025s01e37",
        "logo": "https://image.tmdb.org/t/p/w185/ikLPBoxIzUL8OhIm21kV1V4TcIh.jpg",
        "url": "http://drz.flixip.icu:80/series/2h08bd3p9k/gxhviruvbg/1900954.ts",
        "categories": [
            "ar| سلمى (2025)"
        ],
        "country": ""
    }
]