[
    {
        "name": "Nour El Sham ARB",
        "id": "nourelshamarb",
        "logo": "",
        "url": "http://edinpajalic.streamtv.to:8080/sasodaniel2/GTG53de3f3erFR/4903",
        "categories": [
            "arb syria"
        ],
        "country": ""
    },
    {
        "name": "Sham TV ARB",
        "id": "shamtvarb",
        "logo": "",
        "url": "http://edinpajalic.streamtv.to:8080/sasodaniel2/GTG53de3f3erFR/90929",
        "categories": [
            "arb syria"
        ],
        "country": ""
    },
    {
        "name": "Sama Syria TV ARB",
        "id": "samasyriatvarb",
        "logo": "",
        "url": "http://edinpajalic.streamtv.to:8080/sasodaniel2/GTG53de3f3erFR/2407",
        "categories": [
            "arb syria"
        ],
        "country": ""
    }
]