[
    {
        "name": "DE: Sky Cinema Premieren Highlights FHD",
        "id": "deskycinemapremierenhighlightsfhd",
        "logo": "",
        "url": "http://iptvmeister.de:8080/Erolkirval/zNjKCGEHGPcjA7S41/412046",
        "categories": [
            "de | sky cinema"
        ],
        "country": ""
    },
    {
        "name": "DE: Sky Atlantic FHD",
        "id": "deskyatlanticfhd",
        "logo": "",
        "url": "http://iptvmeister.de:8080/Erolkirval/zNjKCGEHGPcjA7S41/412055",
        "categories": [
            "de | sky cinema"
        ],
        "country": ""
    },
    {
        "name": "DE: SKY SELECT 5",
        "id": "deskyselect5",
        "logo": "",
        "url": "http://iptvmeister.de:8080/Erolkirval/zNjKCGEHGPcjA7S41/412067",
        "categories": [
            "de | sky cinema"
        ],
        "country": ""
    },
    {
        "name": "DE: SKY SELECT 7",
        "id": "deskyselect7",
        "logo": "",
        "url": "http://iptvmeister.de:8080/Erolkirval/zNjKCGEHGPcjA7S41/412069",
        "categories": [
            "de | sky cinema"
        ],
        "country": ""
    },
    {
        "name": "DE: 13TH STREET FHD",
        "id": "de13thstreetfhd",
        "logo": "",
        "url": "http://iptvmeister.de:8080/Erolkirval/zNjKCGEHGPcjA7S41/412081",
        "categories": [
            "de | sky cinema"
        ],
        "country": ""
    }
]