[
    {
        "name": "SWE: TV 10",
        "id": "swetv10",
        "logo": "",
        "url": "http://vipkspkuxae.top:8080/VIP019141747567864457/3cb1de889b92/2326",
        "categories": [
            "eu | sweden vip"
        ],
        "country": ""
    },
    {
        "name": "SWE: VIASAT FOTBOLL",
        "id": "sweviasatfotboll",
        "logo": "https://docdog.top/logo/countries/sweden/viasatfotboll.png",
        "url": "http://vipkspkuxae.top:8080/henri/henri/2268",
        "categories": [
            "eu | sweden vip"
        ],
        "country": ""
    },
    {
        "name": "SWE: TV 6",
        "id": "swetv6",
        "logo": "https://docdog.top/logo/countries/sweden/tv6.png",
        "url": "http://vipkspkuxae.top:8080/VIP0141174316951551/01743169515416/2324",
        "categories": [
            "eu | sweden vip"
        ],
        "country": ""
    },
    {
        "name": "SWE: BOOMERANG",
        "id": "sweboomerang",
        "logo": "https://docdog.top/logo/countries/sweden/boomerang.png",
        "url": "http://vipkspkuxae.top:8080/VIP0141174316951551/01743169515416/2274",
        "categories": [
            "eu | sweden vip"
        ],
        "country": ""
    },
    {
        "name": "SWE: C MORE HITS",
        "id": "swecmorehits",
        "logo": "https://docdog.top/logo/countries/sweden/cmorehits.png",
        "url": "http://vipkspkuxae.top:8080/VIP0141174316951551/01743169515416/2277",
        "categories": [
            "eu | sweden vip"
        ],
        "country": ""
    },
    {
        "name": "SWE: C MORE LIVE 5",
        "id": "swecmorelive5",
        "logo": "https://docdog.top/logo/countries/sweden/cmorelive5.png",
        "url": "http://vipkspkuxae.top:8080/VIP0141174316951551/01743169515416/2283",
        "categories": [
            "eu | sweden vip"
        ],
        "country": ""
    },
    {
        "name": "SWE: CARTOON NETWORK",
        "id": "swecartoonnetwork",
        "logo": "https://docdog.top/logo/countries/sweden/cartoonnetwork.png",
        "url": "http://vipkspkuxae.top:8080/VIP0141174316951551/01743169515416/2286",
        "categories": [
            "eu | sweden vip"
        ],
        "country": ""
    },
    {
        "name": "SWE: SF-KANALEN",
        "id": "swesfkanalen",
        "logo": "",
        "url": "http://vipkspkuxae.top:8080/VIP0141174316951551/01743169515416/2308",
        "categories": [
            "eu | sweden vip"
        ],
        "country": ""
    },
    {
        "name": "SWE: VIASAT HISTORY",
        "id": "sweviasathistory",
        "logo": "https://docdog.top/logo/countries/sweden/viasathistory.png",
        "url": "http://vipkspkuxae.top:8080/VIP0141174316951551/01743169515416/2333",
        "categories": [
            "eu | sweden vip"
        ],
        "country": ""
    },
    {
        "name": "SWE: ANIMAL PLANET",
        "id": "sweanimalplanet",
        "logo": "https://docdog.top/logo/countries/sweden/animalplanet.png",
        "url": "http://vipkspkuxae.top:8080/VIP01798172691513499/672d4b437a1c/2271",
        "categories": [
            "eu | sweden vip"
        ],
        "country": ""
    },
    {
        "name": "SWE: SVT 24/B",
        "id": "swesvt24b",
        "logo": "",
        "url": "http://31.43.191.125:8080/VIP011651756141415591/fdc0fd87f83a/2313",
        "categories": [
            "eu | sweden vip"
        ],
        "country": ""
    }
]