[
    {
        "name": "FR: NRJ HITS FHD",
        "id": "frnrjhitsfhd",
        "logo": "http://sltv-icon.cms-s.com/logo/FRANCE/FHDNRJ12FHD.png",
        "url": "http://ip.sltv.nl:8080/Momokuyen67/KisT5PeotB/218629",
        "categories": [
            "fr musique"
        ],
        "country": ""
    },
    {
        "name": "FR: MCM FHD",
        "id": "frmcmfhd",
        "logo": "http://sltv-icon.cms-s.com/logo/FRANCE/MCMHD.png",
        "url": "http://ip.sltv.nl:8080/Momokuyen67/KisT5PeotB/218619",
        "categories": [
            "fr musique"
        ],
        "country": ""
    },
    {
        "name": "FR: MTV FHD",
        "id": "frmtvfhd",
        "logo": "http://sltv-icon.cms-s.com/logo/germanynew/mtv.png",
        "url": "http://ip.sltv.nl:8080/Momokuyen67/KisT5PeotB/218623",
        "categories": [
            "fr musique"
        ],
        "country": ""
    },
    {
        "name": "FR: TRACE URBAN",
        "id": "frtraceurban",
        "logo": "http://sltv-icon.cms-s.com/logo/franceT-220x132/trace-urban.png",
        "url": "http://ip.sltv.nl:8080/Momokuyen67/KisT5PeotB/13215",
        "categories": [
            "fr musique"
        ],
        "country": ""
    },
    {
        "name": "FR: TRACE GOSPEL",
        "id": "frtracegospel",
        "logo": "http://sltv-icon.cms-s.com/logo/franceT-220x132/trace-gospel.png",
        "url": "http://ip.sltv.nl:8080/Momokuyen67/KisT5PeotB/94573",
        "categories": [
            "fr musique"
        ],
        "country": ""
    },
    {
        "name": "FR: MELODY FHD",
        "id": "frmelodyfhd",
        "logo": "http://sltv-icon.cms-s.com/logo/franceT-220x132/MELODY.png",
        "url": "http://ip.sltv.nl:8080/Momokuyen67/KisT5PeotB/188526",
        "categories": [
            "fr musique"
        ],
        "country": ""
    },
    {
        "name": "FR: CLUBBING TV",
        "id": "frclubbingtv",
        "logo": "",
        "url": "http://ip.sltv.nl:8080/Momokuyen67/KisT5PeotB/653253",
        "categories": [
            "fr musique"
        ],
        "country": ""
    },
    {
        "name": "FR: TRACE CARIBBEAN",
        "id": "frtracecaribbean",
        "logo": "",
        "url": "http://ip.sltv.nl:8080/Momokuyen67/KisT5PeotB/653251",
        "categories": [
            "fr musique"
        ],
        "country": ""
    }
]