[
    {
        "name": "FR: BFM DICI HAUTE PROVENCE",
        "id": "frbfmdicihauteprovence",
        "logo": "",
        "url": "http://ip.sltv.nl:8080/Momokuyen67/KisT5PeotB/653260",
        "categories": [
            "fr pluto - rakuten"
        ],
        "country": ""
    },
    {
        "name": "FR: FILM RISE LES ROUTES DU PARADIS",
        "id": "frfilmriselesroutesduparadis",
        "logo": "",
        "url": "http://ip.sltv.nl:8080/Momokuyen67/KisT5PeotB/610417",
        "categories": [
            "fr pluto - rakuten"
        ],
        "country": ""
    },
    {
        "name": "FR: RAKUTEN TV FILMS DRAMES",
        "id": "frrakutentvfilmsdrames",
        "logo": "https://sltv-icon.cms-s.com/logo/franceT-220x132/RAKUTEN.png",
        "url": "http://ip.sltv.nl:8080/Momokuyen67/KisT5PeotB/610383",
        "categories": [
            "fr pluto - rakuten"
        ],
        "country": ""
    },
    {
        "name": "FR: BFM GRAND LILLE",
        "id": "frbfmgrandlille",
        "logo": "",
        "url": "http://ip.sltv.nl:8080/Momokuyen67/KisT5PeotB/653259",
        "categories": [
            "fr pluto - rakuten"
        ],
        "country": ""
    },
    {
        "name": "FR: BFM MARSEILLE PROVENCE",
        "id": "frbfmmarseilleprovence",
        "logo": "",
        "url": "http://ip.sltv.nl:8080/Momokuyen67/KisT5PeotB/653257",
        "categories": [
            "fr pluto - rakuten"
        ],
        "country": ""
    }
]