[
    {
        "name": "IN: Aastha Bhajan",
        "id": "inaasthabhajan",
        "logo": "http://s3.i3ns.net:2052/portal/picon/2024-12/3e5b3627ae7b2a4e1a1699d8ed8d9885.png",
        "url": "http://013tv.com:8080/silversatcom/uSKcm5tNBsrJ2HZE/193031",
        "categories": [
            "india ➾ lifestyle"
        ],
        "country": ""
    },
    {
        "name": "IN: Aastha Gujarati",
        "id": "inaasthagujarati",
        "logo": "http://s3.i3ns.net:2052/portal/picon/2024-12/fc9cdfc103ebee6d962abf966d00e7f2.png",
        "url": "http://013tv.com:8080/silversatcom/uSKcm5tNBsrJ2HZE/306106",
        "categories": [
            "india ➾ lifestyle"
        ],
        "country": ""
    },
    {
        "name": "IN: Aastha Prime",
        "id": "inaasthaprime",
        "logo": "http://s3.i3ns.net:2052/portal/picon/2025-03/0b8f2ac97b93db1256298c688136600f.png",
        "url": "http://013tv.com:8080/silversatcom/uSKcm5tNBsrJ2HZE/306547",
        "categories": [
            "india ➾ lifestyle"
        ],
        "country": ""
    },
    {
        "name": "IN: Aastha Tamil",
        "id": "inaasthatamil",
        "logo": "http://s3.i3ns.net:2052/portal/picon/2025-03/15c5f064f06580712ef0f2551ba4eae1.png",
        "url": "http://013tv.com:8080/silversatcom/uSKcm5tNBsrJ2HZE/306548",
        "categories": [
            "india ➾ lifestyle"
        ],
        "country": ""
    },
    {
        "name": "IN: Aastha Telugu",
        "id": "inaasthatelugu",
        "logo": "http://s3.i3ns.net:2052/portal/picon/2025-03/3c5f3fe739605103302ad3fdb557aef4.png",
        "url": "http://013tv.com:8080/silversatcom/uSKcm5tNBsrJ2HZE/306546",
        "categories": [
            "india ➾ lifestyle"
        ],
        "country": ""
    },
    {
        "name": "IN: Aastha TV",
        "id": "inaasthatv",
        "logo": "http://s3.i3ns.net:2052/portal/picon/2021-06/13355aca97c24ac469d51750cfcd38a6.png",
        "url": "http://013tv.com:8080/silversatcom/uSKcm5tNBsrJ2HZE/145647",
        "categories": [
            "india ➾ lifestyle"
        ],
        "country": ""
    },
    {
        "name": "IN: Akaal Channel",
        "id": "inakaalchannel",
        "logo": "http://s3.i3ns.net:2052/portal/picon/2023-05/f91eb2182e00b28d0a207c73b16147a9.png",
        "url": "http://013tv.com:8080/silversatcom/uSKcm5tNBsrJ2HZE/165767",
        "categories": [
            "india ➾ lifestyle"
        ],
        "country": ""
    },
    {
        "name": "IN: aur Life",
        "id": "inaurlife",
        "logo": "http://s3.i3ns.net:2052/portal/picon/2025-08/20cb4f37c89d815ec687f1e8f87b7373.png",
        "url": "http://013tv.com:8080/silversatcom/uSKcm5tNBsrJ2HZE/307904",
        "categories": [
            "india ➾ lifestyle"
        ],
        "country": ""
    },
    {
        "name": "IN: Chardikla Time TV",
        "id": "inchardiklatimetv",
        "logo": "http://s3.i3ns.net:2052/portal/picon/2021-06/f7281a291bd837e4222f98954ece1559.png",
        "url": "http://013tv.com:8080/silversatcom/uSKcm5tNBsrJ2HZE/49637",
        "categories": [
            "india ➾ lifestyle"
        ],
        "country": ""
    },
    {
        "name": "IN: Colors Rishtey Asia",
        "id": "incolorsrishteyasia",
        "logo": "http://s3.i3ns.net:2052/portal/picon/2025-03/5f2a4d202220fb78ab06f61fbc1de3ea.png",
        "url": "http://013tv.com:8080/silversatcom/uSKcm5tNBsrJ2HZE/306557",
        "categories": [
            "india ➾ lifestyle"
        ],
        "country": ""
    },
    {
        "name": "IN: Dangal 2",
        "id": "indangal2",
        "logo": "http://s3.i3ns.net:2052/portal/picon/2025-03/e0ff2892b3845684a5283e1c10f9f4cf.png",
        "url": "http://013tv.com:8080/silversatcom/uSKcm5tNBsrJ2HZE/306542",
        "categories": [
            "india ➾ lifestyle"
        ],
        "country": ""
    },
    {
        "name": "IN: Dangal TV",
        "id": "indangaltv",
        "logo": "http://s3.i3ns.net:2052/portal/picon/2025-03/b8a3e3fa9a4f003e5cbdd2a73e51ccf0.png",
        "url": "http://013tv.com:8080/silversatcom/uSKcm5tNBsrJ2HZE/82589",
        "categories": [
            "india ➾ lifestyle"
        ],
        "country": ""
    },
    {
        "name": "IN: DD Assam",
        "id": "inddassam",
        "logo": "http://s3.i3ns.net:2052/portal/picon/2025-02/605c6cfd83333208a2dcf60336a87bb2.png",
        "url": "http://013tv.com:8080/silversatcom/uSKcm5tNBsrJ2HZE/306517",
        "categories": [
            "india ➾ lifestyle"
        ],
        "country": ""
    },
    {
        "name": "IN: DD Bharati",
        "id": "inddbharati",
        "logo": "http://s3.i3ns.net:2052/portal/picon/2023-05/6c7a9ac9923e5cc632a3603f2ef354a4.png",
        "url": "http://013tv.com:8080/silversatcom/uSKcm5tNBsrJ2HZE/193040",
        "categories": [
            "india ➾ lifestyle"
        ],
        "country": ""
    },
    {
        "name": "IN: DD Chandana",
        "id": "inddchandana",
        "logo": "http://s3.i3ns.net:2052/portal/picon/2024-07/75fa98fe7a15a40b9a4432376f41ac04.png",
        "url": "http://013tv.com:8080/silversatcom/uSKcm5tNBsrJ2HZE/82593",
        "categories": [
            "india ➾ lifestyle"
        ],
        "country": ""
    },
    {
        "name": "IN: DD National",
        "id": "inddnational",
        "logo": "http://s3.i3ns.net:2052/portal/picon/2025-03/16033142afbcb5e445d07619ca34ebb9.png",
        "url": "http://013tv.com:8080/silversatcom/uSKcm5tNBsrJ2HZE/192197",
        "categories": [
            "india ➾ lifestyle"
        ],
        "country": ""
    },
    {
        "name": "IN: DD Odia",
        "id": "inddodia",
        "logo": "http://s3.i3ns.net:2052/portal/picon/2025-03/d18f169ced82f6aa35f72bd45ee08dac.png",
        "url": "http://013tv.com:8080/silversatcom/uSKcm5tNBsrJ2HZE/193046",
        "categories": [
            "india ➾ lifestyle"
        ],
        "country": ""
    }
]