[
    {
        "name": "MEX: MULTIMEDIOS",
        "id": "mexmultimedios",
        "logo": "https://docdog.top/logo/countries/mexico/multimedios-mx.png",
        "url": "http://vipbhbiss.top:8080/VIP016621764008551132/a1dbc86008c8/5187",
        "categories": [
            "lame | mexico vip"
        ],
        "country": ""
    },
    {
        "name": "MEX: CARTOON NETWORK",
        "id": "mexcartoonnetwork",
        "logo": "https://docdog.top/logo/countries/mexico/cartoonito-mx.png",
        "url": "http://vipbhbiss.top:8080/VIP014081765268833157/dd7d22aadd59/5102",
        "categories": [
            "lame | mexico vip"
        ],
        "country": ""
    },
    {
        "name": "MEX: NICKTOONS",
        "id": "mexnicktoons",
        "logo": "https://docdog.top/logo/countries/mexico/nicktoons.png",
        "url": "http://vipbhbiss.top:8080/VIP016131749896365487/d53c4c8a5004/5195",
        "categories": [
            "lame | mexico vip"
        ],
        "country": ""
    },
    {
        "name": "MEX: NAT GEO WILD",
        "id": "mexnatgeowild",
        "logo": "https://docdog.top/logo/countries/mexico/natgeowild.png",
        "url": "http://vipbhbiss.top:8080/VIP016571763906336130/d4752a7fef16/5190",
        "categories": [
            "lame | mexico vip"
        ],
        "country": ""
    },
    {
        "name": "MEX: TELEFORMULA",
        "id": "mexteleformula",
        "logo": "https://docdog.top/logo/countries/mexico/countrypic.png",
        "url": "http://vipbhbiss.top:8080/VIP01732172232522092/b435f6385afc/5208",
        "categories": [
            "lame | mexico vip"
        ],
        "country": ""
    },
    {
        "name": "MEX: AYM SPORTS",
        "id": "mexaymsports",
        "logo": "https://docdog.top/logo/countries/mexico/aymsports.png",
        "url": "http://vipneeene.top:8080/VIP0199169358094917/21693580949/5111",
        "categories": [
            "lame | mexico vip"
        ],
        "country": ""
    },
    {
        "name": "MEX: AZ CORAZON",
        "id": "mexazcorazon",
        "logo": "https://docdog.top/logo/countries/mexico/azteca-mx.png",
        "url": "http://vipneeene.top:8080/VIP0199169358094917/21693580949/5114",
        "categories": [
            "lame | mexico vip"
        ],
        "country": ""
    },
    {
        "name": "MEX: CINECANAL",
        "id": "mexcinecanal",
        "logo": "https://docdog.top/logo/countries/mexico/cinecanal.png",
        "url": "http://vipneeene.top:8080/VIP0199169358094917/21693580949/5133",
        "categories": [
            "lame | mexico vip"
        ],
        "country": ""
    },
    {
        "name": "MEX: HISTORY",
        "id": "mexhistory",
        "logo": "https://docdog.top/logo/countries/mexico/historychannel.png",
        "url": "http://vipneeene.top:8080/VIP0199169358094917/21693580949/5172",
        "categories": [
            "lame | mexico vip"
        ],
        "country": ""
    },
    {
        "name": "MEX: ESPN 2",
        "id": "mexespn2",
        "logo": "https://docdog.top/logo/countries/mexico/espn2.png",
        "url": "http://vipneeene.top:8080/SVIP0187173740351071/61746451219116/5153",
        "categories": [
            "lame | mexico vip"
        ],
        "country": ""
    },
    {
        "name": "MEX: TELEVISA",
        "id": "mextelevisa",
        "logo": "https://docdog.top/logo/countries/mexico/televisapueblo.png",
        "url": "http://vipneeene.top:8080/SVIP0187173740351071/61746451219116/5212",
        "categories": [
            "lame | mexico vip"
        ],
        "country": ""
    },
    {
        "name": "MEX: BITME",
        "id": "mexbitme",
        "logo": "https://docdog.top/logo/countries/mexico/countrypic.png",
        "url": "http://vipneeene.top:8080/SVIP0187173740351071/61746451219116/5213",
        "categories": [
            "lame | mexico vip"
        ],
        "country": ""
    },
    {
        "name": "MEX: UNICABLE",
        "id": "mexunicable",
        "logo": "https://docdog.top/logo/countries/mexico/unicable-mx.png",
        "url": "http://vipneeene.top:8080/SVIP0187173740351071/61746451219116/5224",
        "categories": [
            "lame | mexico vip"
        ],
        "country": ""
    },
    {
        "name": "MEX: A&AMP;E",
        "id": "mexaampe",
        "logo": "https://docdog.top/logo/countries/mexico/ae.png",
        "url": "http://vipneeene.top:8080/vip511767980879/p5kxyy9p4bnz/5103",
        "categories": [
            "lame | mexico vip"
        ],
        "country": ""
    },
    {
        "name": "MEX: DISCOVERY CHANNEL",
        "id": "mexdiscoverychannel",
        "logo": "https://docdog.top/logo/countries/mexico/discoverychannel.png",
        "url": "http://vipneeene.top:8080/vip511767980879/p5kxyy9p4bnz/5139",
        "categories": [
            "lame | mexico vip"
        ],
        "country": ""
    },
    {
        "name": "MEX: DISCOVERY CIVILIZATION",
        "id": "mexdiscoverycivilization",
        "logo": "https://docdog.top/logo/countries/mexico/discoverycivilization.png",
        "url": "http://vipneeene.top:8080/vip511767980879/p5kxyy9p4bnz/5140",
        "categories": [
            "lame | mexico vip"
        ],
        "country": ""
    },
    {
        "name": "MEX: DW",
        "id": "mexdw",
        "logo": "https://docdog.top/logo/countries/mexico/dwenglish.png",
        "url": "http://vipneeene.top:8080/vip511767980879/p5kxyy9p4bnz/5150",
        "categories": [
            "lame | mexico vip"
        ],
        "country": ""
    },
    {
        "name": "MEX: SYFY",
        "id": "mexsyfy",
        "logo": "https://docdog.top/logo/countries/mexico/syfy.png",
        "url": "http://vipneeene.top:8080/vip511767980879/p5kxyy9p4bnz/5204",
        "categories": [
            "lame | mexico vip"
        ],
        "country": ""
    },
    {
        "name": "MEX: EL GOURMET",
        "id": "mexelgourmet",
        "logo": "https://docdog.top/logo/countries/mexico/elgourmet.png",
        "url": "http://vipneeene.top:8080/ivanexerr/Guy8qeHkLQ8P/5152",
        "categories": [
            "lame | mexico vip"
        ],
        "country": ""
    },
    {
        "name": "MEX: GOLDEN EDGE",
        "id": "mexgoldenedge",
        "logo": "https://docdog.top/logo/countries/mexico/golden-edge-mx.png",
        "url": "http://vipbhbiss.top:8080/VIP019881756791198618/8032b46f0b73/5169",
        "categories": [
            "lame | mexico vip"
        ],
        "country": ""
    },
    {
        "name": "MEX: SPACE",
        "id": "mexspace",
        "logo": "https://docdog.top/logo/countries/mexico/space.png",
        "url": "http://vipbhbiss.top:8080/VIP016621764008551132/a1dbc86008c8/5201",
        "categories": [
            "lame | mexico vip"
        ],
        "country": ""
    },
    {
        "name": "MEX: AMC",
        "id": "mexamc",
        "logo": "https://docdog.top/logo/countries/mexico/amc.png",
        "url": "http://vipbhbiss.top:8080/VIP016571763906336130/d4752a7fef16/5107",
        "categories": [
            "lame | mexico vip"
        ],
        "country": ""
    },
    {
        "name": "MEX: TNT SERIES",
        "id": "mextntseries",
        "logo": "https://docdog.top/logo/countries/mexico/tntseries.png",
        "url": "http://vipbhbiss.top:8080/VIP016571763906336130/d4752a7fef16/5217",
        "categories": [
            "lame | mexico vip"
        ],
        "country": ""
    },
    {
        "name": "MEX: FX",
        "id": "mexfx",
        "logo": "https://docdog.top/logo/countries/mexico/fx.png",
        "url": "http://vipbhbiss.top:8080/VIP01732172232522092/b435f6385afc/5165",
        "categories": [
            "lame | mexico vip"
        ],
        "country": ""
    },
    {
        "name": "MEX: DISNEY JR",
        "id": "mexdisneyjr",
        "logo": "https://docdog.top/logo/countries/mexico/disneyjr.png",
        "url": "http://vipneeene.top:8080/vip9721770573308/181155a03f11/5148",
        "categories": [
            "lame | mexico vip"
        ],
        "country": ""
    },
    {
        "name": "MEX: TVC DEPORTES",
        "id": "mextvcdeportes",
        "logo": "https://docdog.top/logo/countries/mexico/countrypic.png",
        "url": "http://vipneeene.top:8080/vip9721770573308/181155a03f11/5223",
        "categories": [
            "lame | mexico vip"
        ],
        "country": ""
    },
    {
        "name": "MEX: ANIMAL PLANET",
        "id": "mexanimalplanet",
        "logo": "https://docdog.top/logo/countries/mexico/animalplanet.png",
        "url": "http://vipneeene.top:8080/VIP015601764578447144/17b9d0579446/5108",
        "categories": [
            "lame | mexico vip"
        ],
        "country": ""
    }
]