[
    {
        "name": "USA: NFL NETWORK (1)",
        "id": "usanflnetwork1",
        "logo": "",
        "url": "http://1tv41.icu:8080/ahx4CN/815233/159091",
        "categories": [
            "nfl"
        ],
        "country": ""
    },
    {
        "name": "USA | NFL",
        "id": "usanfl",
        "logo": "",
        "url": "http://xxip25.top:8080/hVvwU8/670199/208896",
        "categories": [
            "nfl"
        ],
        "country": ""
    },
    {
        "name": "USA | NFL REDZONE 3",
        "id": "usanflredzone3",
        "logo": "",
        "url": "http://xxip25.top:8080/c1E50nv/32NYwus8o2/208830",
        "categories": [
            "nfl"
        ],
        "country": ""
    },
    {
        "name": "NFL 03:  Super Bowl LX",
        "id": "nfl03superbowllx",
        "logo": "",
        "url": "http://xxip25.top:8080/hVvwU8/670199/252012",
        "categories": [
            "nfl"
        ],
        "country": ""
    },
    {
        "name": "US NFL Network",
        "id": "usnflnetwork",
        "logo": "https://i.dlpng.com/static/png/5438735-nfl-team-logos-transparent-png-history-logos-lists-brands-nfl-logo-png-300_300_preview.png",
        "url": "http://mytvstream.net:8080/RKu2Hy/559290/83724",
        "categories": [
            "nfl"
        ],
        "country": ""
    }
]