[
    {
        "name": "NO: Food Network",
        "id": "nofoodnetwork",
        "logo": "https://upload.wikimedia.org/wikipedia/commons/thumb/f/f9/Food_Network_New_Logo.png/615px-Food_Network_New_Logo.png",
        "url": "http://supiptv.vip:8080/xg0kF4Uq/f685eCma/178670",
        "categories": [
            "norway - dokumentarer & livsstil"
        ],
        "country": ""
    },
    {
        "name": "NO: Nat Geo Wild HD [Multi-Sub]",
        "id": "nat geo wild.no",
        "logo": "[",
        "url": "http://supiptv.vip:8080/xg0kF4Uq/f685eCma/176940",
        "categories": [
            "norway - dokumentarer & livsstil"
        ],
        "country": ""
    },
    {
        "name": "NO: Viasat History FHD [Multi-Sub]",
        "id": "noviasathistoryfhdmultisub",
        "logo": "https://upload.wikimedia.org/wikipedia/commons/thumb/2/21/Viasat_History-logo.svg/150px-Viasat_History-logo.svg.png",
        "url": "http://supiptv.vip:8080/xg0kF4Uq/f685eCma/183109",
        "categories": [
            "norway - dokumentarer & livsstil"
        ],
        "country": ""
    }
]