[
    {
        "name": "TR: TRT SPOR 2 HD",
        "id": "trtrtspor2hd",
        "logo": "",
        "url": "http://vipkspkuxae.top:8080/VIP0141174316951551/01743169515416/141448",
        "categories": [
            "tr | sport vip"
        ],
        "country": ""
    },
    {
        "name": "TR: TRT SPOR HD",
        "id": "trtrtsporhd",
        "logo": "https://docdog.top/logo/countries/turkey/trt-spor-tr.png",
        "url": "http://vipkspkuxae.top:8080/VIP011661747712236459/baa98ca8e739/141449",
        "categories": [
            "tr | sport vip"
        ],
        "country": ""
    },
    {
        "name": "TR: BEIN SPORTS MAX 1 FHD",
        "id": "trbeinsportsmax1fhd",
        "logo": "https://docdog.top/logo/countries/turkey/beinsportsmax1.png",
        "url": "http://vipkspkuxae.top:8080/VIP01798172691513499/672d4b437a1c/141372",
        "categories": [
            "tr | sport vip"
        ],
        "country": ""
    },
    {
        "name": "TR: BEIN SPORTS HABER HD",
        "id": "trbeinsportshaberhd",
        "logo": "https://docdog.top/logo/countries/turkey/bein-sports-haber-tr.png",
        "url": "http://vipkspkuxae.top:8080/VIP01545171425617373/ca75a1a2314d/141371",
        "categories": [
            "tr | sport vip"
        ],
        "country": ""
    },
    {
        "name": "TR: BEIN SPORTS 1 SD",
        "id": "trbeinsports1sd",
        "logo": "https://docdog.top/logo/countries/turkey/beinsports1.png",
        "url": "http://vipketseyket.top:8080/VIP014901749838374486/902896e075e8/141357",
        "categories": [
            "tr | sport vip"
        ],
        "country": ""
    }
]